oaix.py
oaix-0.1.0.dist-info/LICENSE
oaix-0.1.0.dist-info/WHEEL
oaix-0.1.0.dist-info/METADATA
oaix-0.1.0.dist-info/RECORD
