Metadata-Version: 2.1
Name: oaix
Version: 0.1.0
Summary: A minimalist client for OpenAI APIs.
Author-email: Chris Coleman <chris@chriscoleman.uk>
Classifier: License :: OSI Approved :: MIT License
Requires-Dist: confuse
Requires-Dist: httpx
